{
  "id": "venue_25f61576b1e7",
  "name_en": "Borgo Trento District",
  "name_local": "Borgo Trento",
  "icon": "map",
  "lat": 45.442,
  "lon": 10.988,
  "radius_m": 1000,
  "phrases": [
    {
      "id": "it_bt_vr_001",
      "intent_en": "Ask how to cross to Borgo Trento from the historic centre",
      "text_local": "Scusi, come si raggiunge il Borgo Trento dal centro?",
      "pronunciation": "SKOO-zee, KOH-meh see raj-JOO-njeh eel BOR-goh TREN-toh dal CHEN-troh?",
      "formality": "polite",
      "cultural_note": "Borgo Trento is Verona's quiet residential neighbourhood across the Adige River — peaceful and away from tourist crowds.",
      "speech_act": "request",
      "expects_reply": true,
      "responses": [
        {
          "english": "From Ponte Pietra, cross the river on foot.",
          "phonetic": "dal PON-teh PYEH-trah, at-trah-VER-sah eel FYOO-meh ah PYEH-dee.",
          "local": "Dal Ponte Pietra, attraversa il fiume a piedi."
        }
      ]
    },
    {
      "id": "it_bt_vr_002",
      "intent_en": "Ask where the Teatro Romano is",
      "text_local": "Buongiorno, dov'è il Teatro Romano di Verona?",
      "pronunciation": "bwohn-JOHR-noh, doh-VEH eel teh-AH-troh roh-MAH-noh dee veh-ROH-nah?",
      "formality": "polite",
      "cultural_note": "",
      "speech_act": "request",
      "expects_reply": true,
      "responses": [
        {
          "english": "On the San Pietro hill, above Ponte Pietra.",
          "phonetic": "sool KOL-leh dee san PYEH-troh, SOH-prah eel PON-teh PYEH-trah.",
          "local": "Sul colle di San Pietro, sopra il Ponte Pietra."
        }
      ]
    },
    {
      "id": "it_bt_vr_003",
      "intent_en": "Ask if the funicular to the Castel San Pietro is running",
      "text_local": "Scusi, funziona la funicolare per il Castel San Pietro?",
      "pronunciation": "SKOO-zee, foon-TSYOH-nah lah foo-nee-koh-LAH-reh per eel KAS-tel san PYEH-troh?",
      "formality": "polite",
      "cultural_note": "",
      "speech_act": "question",
      "expects_reply": true,
      "responses": [
        {
          "english": "Yes, it departs from the riverside, every twenty minutes.",
          "phonetic": "see, PAR-teh dal loon-gah-DEE-jeh, ON-nyee VEN-tee mee-NOO-tee.",
          "local": "Sì, parte dal lungadige, ogni venti minuti."
        }
      ]
    },
    {
      "id": "it_bt_vr_004",
      "intent_en": "Ask where to get a panoramic view of Verona",
      "text_local": "Buongiorno, dov'è il punto panoramico migliore su Verona?",
      "pronunciation": "bwohn-JOHR-noh, doh-VEH eel POON-toh pah-noh-RAH-mee-koh meel-YOH-reh soo veh-ROH-nah?",
      "formality": "polite",
      "cultural_note": "",
      "speech_act": "request",
      "expects_reply": true,
      "responses": [
        {
          "english": "From Castel San Pietro, view of the whole city.",
          "phonetic": "dal KAS-tel san PYEH-troh, VEES-tah soo TOOT-tah lah cheet-TAH.",
          "local": "Dal Castel San Pietro, vista su tutta la città."
        }
      ]
    },
    {
      "id": "it_bt_vr_005",
      "intent_en": "Ask if there are good restaurants in Borgo Trento",
      "text_local": "Scusi, ci sono ristoranti tipici nel Borgo Trento?",
      "pronunciation": "SKOO-zee, chee SOH-noh rees-toh-RAN-tee TEE-pee-chee nel BOR-goh TREN-toh?",
      "formality": "polite",
      "cultural_note": "",
      "speech_act": "question",
      "expects_reply": true,
      "responses": [
        {
          "english": "Yes, a few local trattorias, less touristy than the centre.",
          "phonetic": "see, KWAL-keh trat-toh-REE-ah loh-KAH-leh, MEH-noh too-REES-tee-kah del CHEN-troh.",
          "local": "Sì, qualche trattoria locale, meno turistica del centro."
        }
      ]
    }
  ],
  "vocabulary": []
}