{
  "id": "konya_meram_bağları_vineyards",
  "name_en": "Meram Bağları vineyards",
  "name_local": "Meram Bağları",
  "icon": "leaf",
  "lat": 37.872734,
  "lon": 32.4924376,
  "radius_m": 300,
  "phrases": [
    {
      "id": "konya_meram_bağları_vineyards_001",
      "intent_en": "Is there parking fee?",
      "text_local": "Otopark ücretli mi?",
      "pronunciation": "ohtohpAHrk-uhdzhrehtlIH-mih",
      "formality": "standard",
      "cultural_note": "Meram Bağları'nda otopark ücreti uygulaması bölgeye göre değişiklik gösterebilir.",
      "speech_act": "question",
      "expects_reply": true,
      "likely_response": {
        "local": "Bazı alanlarda ücretlidir.",
        "pronunciation": "bahzOO-ahahnahrdAH-uhdzhrehtlEEdihr",
        "translation_en": "There is a fee in some areas."
      },
      "responses": [
        {
          "english": "There is a fee in some areas.",
          "phonetic": "bahzOO-ahahnahrdAH-uhdzhrehtlEEdihr",
          "french": "Bazı alanlarda ücretlidir."
        }
      ]
    },
    {
      "id": "konya_meram_bağları_vineyards_002",
      "intent_en": "Where is Meram Bridge?",
      "text_local": "Meram Köprüsü nerede?",
      "pronunciation": "mehrAHm-kuhpruesUH-nEHrehdeh",
      "formality": "standard",
      "cultural_note": "Köprü, Meram Deresi üzerinde yer alır ve dere boyu yürüyüş yolu takip edilerek bulunabilir.",
      "speech_act": "question",
      "expects_reply": true,
      "likely_response": {
        "local": "Dere boyunca ilerleyin.",
        "pronunciation": "dehrEH-bohyuhndzhAH-eelehrlehyIHn",
        "translation_en": "Proceed along the stream."
      },
      "responses": [
        {
          "english": "Proceed along the stream.",
          "phonetic": "dehrEH-bohyuhndzhAH-eelehrlehyIHn",
          "french": "Dere boyunca ilerleyin."
        }
      ]
    },
    {
      "id": "konya_meram_bağları_vineyards_003",
      "intent_en": "How do I pay for tea?",
      "text_local": "Çay için nasıl ödeme yapabilirim?",
      "pronunciation": "tshAHy-eetshIHn-nahsOO-uhdEHmeh-yahpahbeelEErihm",
      "formality": "standard",
      "cultural_note": "Çay bahçelerinde hesap genellikle masaya servis yapan garson tarafından tahsil edilir.",
      "speech_act": "question",
      "expects_reply": true,
      "likely_response": {
        "local": "Garsona ödeyin.",
        "pronunciation": "gahrsohnAH-uhdehyIHn",
        "translation_en": "Pay the waiter."
      },
      "responses": [
        {
          "english": "Pay the waiter.",
          "phonetic": "gahrsohnAH-uhdehyIHn",
          "french": "Garsona ödeyin."
        }
      ]
    },
    {
      "id": "konya_meram_bağları_vineyards_004",
      "intent_en": "Where are the family sections?",
      "text_local": "Aile bölümleri nereye denk geliyor?",
      "pronunciation": "ahEEleh-buhluhmlehrIH-nEHrehdeh",
      "formality": "casual",
      "cultural_note": "Aile bölümlerinin konumu genel alan içinde değişkenlik gösterebilir, görevliler en doğru yönlendirmeyi yapacaktır.",
      "speech_act": "question",
      "expects_reply": true,
      "likely_response": {
        "local": "Dere kenarındaki asma korulukları",
        "pronunciation": "dehrEH-kehnahroondahkIH-AHsmah-kohroouhkahrOO",
        "translation_en": "The vine groves by the creek"
      },
      "responses": [
        {
          "english": "The vine groves by the creek",
          "phonetic": "dehrEH-kehnahroondahkIH-AHsmah-kohroouhkahrOO",
          "french": "Dere kenarındaki asma korulukları"
        }
      ]
    },
    {
      "id": "konya_meram_bağları_vineyards_005",
      "intent_en": "Where can I rent a table?",
      "text_local": "Masa kiralama nereden yapılıyor?",
      "pronunciation": "mAHsah-keerAHahmah-nEHrehdahn-yahpooOOyawr",
      "formality": "standard",
      "cultural_note": "Geniş bir alana yayılmış piknik bölgesinde masa kiralama noktaları girişe göre değişiklik gösterebilir.",
      "speech_act": "question",
      "expects_reply": true,
      "likely_response": {
        "local": "Dere kenarındaki görevliye sorun.",
        "pronunciation": "dehrEH-kehnahroondahkIH-uhrehvleeyEH-sohrUHn",
        "translation_en": "Ask the attendant by the stream."
      },
      "responses": [
        {
          "english": "Ask the attendant by the stream.",
          "phonetic": "dehrEH-kehnahroondahkIH-uhrehvleeyEH-sohrUHn",
          "french": "Dere kenarındaki görevliye sorun."
        }
      ]
    }
  ],
  "vocabulary": []
}