{
  "id": "venue_5cb10966b887",
  "name_en": "Barceloneta Beach",
  "name_local": "Platja de la Barceloneta",
  "icon": "sun.max",
  "lat": 41.3793286,
  "lon": 2.192971,
  "radius_m": 300,
  "phrases": [
    {
      "id": "phrase_1bcd20a47dd0",
      "intent_en": "Ask where the showers are",
      "text_local": "Disculpe, ¿sabe dónde hay duchas públicas para usar?",
      "pronunciation": "dees-KOOL-peh, ¿SAH-beh DOHN-deh eye DOO-chahs POO-blee-kahs PAH-rah oo-SAHR?",
      "formality": "polite",
      "cultural_note": "",
      "speech_act": "question",
      "expects_reply": true,
      "likely_response": {
        "local": "Junto al chiringuito 'La Cova', a la derecha.",
        "pronunciation": "HOON-toh AHL chee-reen-g-EE-toh LAH KOH-bah AH LAH deh-REHTH-ah",
        "translation_en": "Next to the public restrooms."
      },
      "responses": [
        {
          "english": "Next to the public restrooms.",
          "phonetic": "HOON-toh AHL chee-reen-g-EE-toh LAH KOH-bah AH LAH deh-REHTH-ah",
          "local": "Junto al chiringuito 'La Cova', a la derecha."
        }
      ]
    },
    {
      "id": "phrase_a15d203b71a1",
      "intent_en": "Ask where to rent sun loungers",
      "text_local": "Buenos días, ¿dónde puedo alquilar tumbonas?",
      "pronunciation": "BWEH-nohs DEE-ahs, DOHN-deh PWEH-doh ahl-KEE-lahr toom-BOH-nahs",
      "formality": "polite",
      "cultural_note": "",
      "speech_act": "question",
      "expects_reply": true,
      "likely_response": {
        "local": "En los chiringuitos azules junto al espigón.",
        "pronunciation": "EHN LOHS chee-reen-g-EE-tohs ah-THOO-lehs HOON-toh AHL eh-spee-GÓN",
        "translation_en": "At the blue stands, near the water."
      },
      "responses": [
        {
          "english": "At the blue stands, near the water.",
          "phonetic": "EHN LOHS chee-reen-g-EE-tohs ah-THOO-lehs HOON-toh AHL eh-spee-GÓN",
          "local": "En los chiringuitos azules junto al espigón."
        }
      ]
    },
    {
      "id": "phrase_785153ac8aa3",
      "intent_en": "Ask where the lifeguard station is",
      "text_local": "Disculpe, ¿dónde está el puesto de socorrismo?",
      "pronunciation": "dees-KOOL-peh, DOHN-deh eh-STAH el PWES-toh deh soh-koh-REES-moh",
      "formality": "polite",
      "cultural_note": "",
      "speech_act": "question",
      "expects_reply": true,
      "likely_response": {
        "local": "En la torre alta, zona central.",
        "pronunciation": "EHN LAH TOHR-reh AHL-tah THOH-nah thehnt-RAHL",
        "translation_en": "At the high tower, central zone."
      },
      "responses": [
        {
          "english": "At the high tower, central zone.",
          "phonetic": "EHN LAH TOHR-reh AHL-tah THOH-nah thehnt-RAHL",
          "local": "En la torre alta, zona central."
        }
      ]
    },
    {
      "id": "phrase_f49d5074eacf",
      "intent_en": "Ask where to rent water sports equipment",
      "text_local": "Buenos días, ¿dónde alquilan equipos de deportes acuáticos?",
      "pronunciation": "BWEH-nos DEE-as, DOHN-deh al-KEE-lahn eh-KEE-pohs deh deh-POR-tes ah-KWAH-tee-kohs?",
      "formality": "polite",
      "cultural_note": "",
      "speech_act": "question",
      "expects_reply": true,
      "likely_response": {
        "local": "En el quiosco grande, al final.",
        "pronunciation": "EHN EHL k-ee-OH-skoh GRAHN-deh AHL fee-NAHL",
        "translation_en": "At the large kiosk, at the end."
      },
      "responses": [
        {
          "english": "At the large kiosk, at the end.",
          "phonetic": "EHN EHL k-ee-OH-skoh GRAHN-deh AHL fee-NAHL",
          "local": "En el quiosco grande, al final."
        }
      ]
    },
    {
      "id": "phrase_e8be3dc298b1",
      "intent_en": "Ask where the changing facilities are",
      "text_local": "Disculpe, ¿dónde están los vestuarios para cambiarse?",
      "pronunciation": "dees-KOOL-peh, DOHN-deh eh-STAHN lohs ves-TWAH-ree-ohs PAH-rah kam-bee-AR-seh",
      "formality": "polite",
      "cultural_note": "",
      "speech_act": "question",
      "expects_reply": true,
      "likely_response": {
        "local": "Junto al chiringuito 'La Cova Fumada'.",
        "pronunciation": "HOON-toh AHL chee-reen-g-EE-toh LAH KOH-bah foo-MAH-dah",
        "translation_en": "Near the main entrance, left side."
      },
      "responses": [
        {
          "english": "Near the main entrance, left side.",
          "phonetic": "HOON-toh AHL chee-reen-g-EE-toh LAH KOH-bah foo-MAH-dah",
          "local": "Junto al chiringuito 'La Cova Fumada'."
        }
      ]
    }
  ],
  "vocabulary": []
}